live_plotter/__init__.py
live_plotter/fast_live_image_plotter_core.py
live_plotter/fast_live_image_plotter_grid_separate_process_core.py
live_plotter/fast_live_plotter_core.py
live_plotter/fast_live_plotter_grid_separate_process_core.py
live_plotter/live_image_plotter_core.py
live_plotter/live_image_plotter_grid_separate_process_core.py
live_plotter/live_plotter_core.py
live_plotter/live_plotter_grid_separate_process_core.py
live_plotter/separate_process_live_plotter_core.py
live_plotter/test.py
live_plotter/testing.py
live_plotter/testing2.py
live_plotter/testing3.py
live_plotter/testing4.py
live_plotter/testing5.py
live_plotter/testing6.py
live_plotter/utils.py
live_plotter-4.1.0.dist-info/LICENSE
live_plotter-4.1.0.dist-info/METADATA
live_plotter-4.1.0.dist-info/WHEEL
live_plotter-4.1.0.dist-info/top_level.txt
live_plotter-4.1.0.dist-info/RECORD
