Metadata-Version: 2.1
Name: live-plotter
Version: 4.1.0
Summary: Plot live data that updates in real time using matplotlib backend
Home-page: https://github.com/tylerlum/live_plotter
Author: Tyler Lum
Author-email: tylergwlum@gmail.com
License: UNKNOWN
Keywords: python,matplotlib,plot,live,real time
Platform: UNKNOWN
Classifier: Intended Audience :: Developers
Classifier: Topic :: Scientific/Engineering :: Visualization
Classifier: License :: OSI Approved :: MIT License
Classifier: Programming Language :: Python :: 3
License-File: LICENSE
Requires-Dist: matplotlib
Requires-Dist: numpy
Requires-Dist: seaborn
